bigdata_util/mr_launcher.py
bigdata_util/connector/__init__.py
bigdata_util/connector/base_query.py
bigdata_util/connector/clickhouse.py
bigdata_util/connector/datahub.py
bigdata_util/connector/datahub_reader.py
bigdata_util/connector/hive.py
bigdata_util/connector/hive_kerberos.py
bigdata_util/connector/kafka.py
bigdata_util/connector/maxcompute.py
bigdata_util/connector/mysql.py
bigdata_util/connector/oss.py
bigdata_util/connector/phoenix.py
bigdata_util/connector/postgre.py
bigdata_util/connector/postgre_async.py
bigdata_util/connector/tablestore.py
bigdata_util/plot/__init__.py
bigdata_util/plot/plot_line.py
bigdata_util/util/__init__.py
bigdata_util/util/angle.py
bigdata_util/util/base_config.py
bigdata_util/util/base_config_new.py
bigdata_util/util/coord_transform_utils.py
bigdata_util/util/csv.py
bigdata_util/util/logger.py
bigdata_util/util/nearest_point.py
bigdata_util/util/network.py
bigdata_util/util/shapely_helper.py
bigdata_util/util/singleton.py
bigdata_util/util/singleton_annotation.py
bigdata_util/util/sql_format.py
bigdata_util/util/str_format.py
bigdata_util/util/table_info.py
bigdata_util/util/time_tick.py
bigdata_util/util/util.py
py_bigdata_util-0.1.0.dist-info/METADATA
py_bigdata_util-0.1.0.dist-info/WHEEL
py_bigdata_util-0.1.0.dist-info/top_level.txt
py_bigdata_util-0.1.0.dist-info/RECORD
